cccs_ipyaggrid-0.5.6.data/data/etc/jupyter/nbconfig/notebook.d/ipyaggrid.json
cccs_ipyaggrid-0.5.6.data/data/share/jupyter/labextensions/ipyaggrid/install.json
cccs_ipyaggrid-0.5.6.data/data/share/jupyter/labextensions/ipyaggrid/package.json
cccs_ipyaggrid-0.5.6.data/data/share/jupyter/labextensions/ipyaggrid/static/155.53a5de97ac75a3cafa41.js
cccs_ipyaggrid-0.5.6.data/data/share/jupyter/labextensions/ipyaggrid/static/486.9a102cac74aa3af2b7b8.js
cccs_ipyaggrid-0.5.6.data/data/share/jupyter/labextensions/ipyaggrid/static/486.9a102cac74aa3af2b7b8.js.LICENSE.txt
cccs_ipyaggrid-0.5.6.data/data/share/jupyter/labextensions/ipyaggrid/static/590.b61372997c91baf23fc4.js
cccs_ipyaggrid-0.5.6.data/data/share/jupyter/labextensions/ipyaggrid/static/590.b61372997c91baf23fc4.js.LICENSE.txt
cccs_ipyaggrid-0.5.6.data/data/share/jupyter/labextensions/ipyaggrid/static/591.89fd4c700b5e9bf9a04d.js
cccs_ipyaggrid-0.5.6.data/data/share/jupyter/labextensions/ipyaggrid/static/628.a876a22b5bf4766eb88f.js
cccs_ipyaggrid-0.5.6.data/data/share/jupyter/labextensions/ipyaggrid/static/680.9780c99311f6aacd0551.js
cccs_ipyaggrid-0.5.6.data/data/share/jupyter/labextensions/ipyaggrid/static/731.0e661d2646511263a3f4.js
cccs_ipyaggrid-0.5.6.data/data/share/jupyter/labextensions/ipyaggrid/static/731.0e661d2646511263a3f4.js.LICENSE.txt
cccs_ipyaggrid-0.5.6.data/data/share/jupyter/labextensions/ipyaggrid/static/906.95bbf22d029b842482b2.js
cccs_ipyaggrid-0.5.6.data/data/share/jupyter/labextensions/ipyaggrid/static/906.95bbf22d029b842482b2.js.LICENSE.txt
cccs_ipyaggrid-0.5.6.data/data/share/jupyter/labextensions/ipyaggrid/static/remoteEntry.bac2672a4dbafb5f5ba0.js
cccs_ipyaggrid-0.5.6.data/data/share/jupyter/labextensions/ipyaggrid/static/style.js
cccs_ipyaggrid-0.5.6.data/data/share/jupyter/labextensions/ipyaggrid/static/third-party-licenses.json
cccs_ipyaggrid-0.5.6.data/data/share/jupyter/nbextensions/ipyaggrid/906.index.js
cccs_ipyaggrid-0.5.6.data/data/share/jupyter/nbextensions/ipyaggrid/extension.js
cccs_ipyaggrid-0.5.6.dist-info/LICENSE
cccs_ipyaggrid-0.5.6.dist-info/METADATA
cccs_ipyaggrid-0.5.6.dist-info/WHEEL
cccs_ipyaggrid-0.5.6.dist-info/top_level.txt
cccs_ipyaggrid-0.5.6.dist-info/RECORD
