Metadata-Version: 2.1
Name: cccs-ipyaggrid
Version: 0.5.6
Summary: Jupyter widget - ag-grid in the notebook
Home-page: https://github.com/widgetti/ipyaggrid
Download-URL: https://github.com/widgetti/ipyaggrid/archive/refs/tags/v0.5.6.zip
Author: Mario Buikhuizen, Maarten Breddels, DGothrek
Author-email: mariobuikhuizen@gmail.com, maartenbreddels@gmail.com
License: MIT
Keywords: ipywidget,javascript,ag-grid
Classifier: Development Status :: 4 - Beta
Classifier: License :: OSI Approved :: MIT License
Classifier: Programming Language :: Python :: 3.5
Classifier: Programming Language :: Python :: 3.6
License-File: LICENSE
Requires-Dist: ipywidgets>=7.4.0
Requires-Dist: pandas
Requires-Dist: simplejson>=3.13.2
Provides-Extra: ui-test
Requires-Dist: solara[pytest]; extra == "ui-test"
Requires-Dist: jupyter-server<2; extra == "ui-test"
Requires-Dist: playwright==1.32.1; extra == "ui-test"
Requires-Dist: jupyterlab==3.6.3; extra == "ui-test"
Provides-Extra: unit-test
Requires-Dist: pytest; extra == "unit-test"
